turnstile/__init__.py
turnstile/apps.py
turnstile/forms.py
turnstile/models.py
turnstile/utils.py
turnstile/widgets.py
turnstile/migrations/0001_initial.py
turnstile/migrations/0002_delete_turnstileabstractformfield.py
turnstile/migrations/__init__.py
turnstile/templates/turnstile/turnstile_widget.html
turnstile/templatetags/__init__.py
turnstile/templatetags/turnstile.py
turnstile/tests/__init__.py
turnstile/tests/test_fields.py
turnstile/tests/test_utils.py
turnstile/tests/test_widgets.py
wagtail_turnstile-0.6.0.dist-info/licenses/LICENSE
wagtail_turnstile-0.6.0.dist-info/METADATA
wagtail_turnstile-0.6.0.dist-info/WHEEL
wagtail_turnstile-0.6.0.dist-info/top_level.txt
wagtail_turnstile-0.6.0.dist-info/RECORD
